l3ac/__about__.py
l3ac/__init__.py
l3ac/codec.py
l3ac/en_codec.py
l3ac/layers.py
l3ac/local_trans.py
l3ac/modules.py
l3ac/configs/0k75bps.toml
l3ac/configs/1k5bps.toml
l3ac/configs/1kbps.toml
l3ac/configs/3kbps.toml
l3ac/configs/debug.toml
l3ac/tconv/__init__.py
l3ac/tconv/base.py
l3ac/vq/__init__.py
l3ac/vq/fsq.py
l3ac/vq/fsq_act.py
l3ac/xtract/__init__.py
l3ac/xtract/config.py
l3ac/xtract/nn/__init__.py
l3ac/xtract/nn/layers.py
l3ac/xtract/nn/module.py
l3ac/xtract/nn/utils.py
l3ac-1.0.dist-info/METADATA
l3ac-1.0.dist-info/WHEEL
l3ac-1.0.dist-info/RECORD
