Metadata-Version: 2.4
Name: l3ac
Version: 1.0
Summary: L3AC: A nerual audio codec with one quantizer
Project-URL: Documentation, https://github.com/zhai-lw/L3AC#readme
Project-URL: Repository, https://github.com/zhai-lw/L3AC.git
Project-URL: Issues, https://github.com/zhai-lw/L3AC/issues
Project-URL: DOWNLOAD, https://huggingface.co/zhai-lw/L3AC
Author-email: Linwei Zhai <zhai_lw@outlook.com>
License-Expression: MIT
Keywords: artificial intelligence,audio codec,deep learning,pytorch
Classifier: Development Status :: 4 - Beta
Classifier: Intended Audience :: Developers
Classifier: Programming Language :: Python
Classifier: Topic :: Scientific/Engineering :: Artificial Intelligence
Requires-Python: >=3.11
Requires-Dist: local-attention==1.11.2
Requires-Dist: pydantic-settings
Requires-Dist: torch>=2.5
Provides-Extra: examples
Requires-Dist: librosa; extra == 'examples'
